LICENSE
MANIFEST.in
README.rst
requirements.txt
requirements_dev.txt
setup.cfg
setup.py
serializabledict/__init__.py
serializabledict.egg-info/PKG-INFO
serializabledict.egg-info/SOURCES.txt
serializabledict.egg-info/dependency_links.txt
serializabledict.egg-info/not-zip-safe
serializabledict.egg-info/requires.txt
serializabledict.egg-info/top_level.txt
serializabledict/storage/__init__.py
serializabledict/storage/common.py
serializabledict/storage/jsonfilestorage.py
serializabledict/storage/jsonformatmixin.py
serializabledict/storage/yamlfilestorage.py
serializabledict/storage/yamlformatmixin.py
tests/__init__.py
tests/test_serializabledict.py