Metadata-Version: 1.1
Name: serializabledict
Version: 0.0.5
Summary: A simple serializable dict
Home-page: https://github.com/starofrainnight/serializabledict
Author: Hong-She Liang
Author-email: starofrainnight@gmail.com
License: Apache Software License
Keywords: serializabledict,serializabledict
Platform: UNKNOWN
Classifier: Development Status :: 3 - Alpha
Classifier: Intended Audience :: Developers
Classifier: License :: OSI Approved :: Apache Software License
Classifier: Natural Language :: English
Classifier: Programming Language :: Python :: 3
Classifier: Programming Language :: Python :: 3.4
Classifier: Programming Language :: Python :: 3.5
Classifier: Programming Language :: Python :: 3.6
